lamine/__init__.py
lamine/tools.py
lamine_root-0.0.12.dist-info/LICENSE
lamine_root-0.0.12.dist-info/METADATA
lamine_root-0.0.12.dist-info/WHEEL
lamine_root-0.0.12.dist-info/top_level.txt
lamine_root-0.0.12.dist-info/RECORD
