Metadata-Version: 2.1
Name: lamine_root
Version: 0.0.12
Summary: use this library in kivy android
Home-page: https://github.com/pypa/sampleproject
Author: Lamine ML
Author-email: lamineml128@gmail.com
Project-URL: Bug Tracker, https://github.com/pypa/sampleproject/issues
Classifier: Programming Language :: Python :: 3
Classifier: License :: OSI Approved :: MIT License
Classifier: Operating System :: OS Independent
Requires-Python: >=3.8
License-File: LICENSE
